pygstuff/__init__.py
pygstuff/clock.py
pygstuff/colors.py
pygstuff/draw_geometry.py
pygstuff/geometry.py
pygstuff/plot.py
pygstuff/user.py
pygstuff/window.py
pygstuff-0.0.3.dist-info/LICENSE.md
pygstuff-0.0.3.dist-info/METADATA
pygstuff-0.0.3.dist-info/WHEEL
pygstuff-0.0.3.dist-info/top_level.txt
pygstuff-0.0.3.dist-info/RECORD
