Metadata-Version: 2.1
Name: pygstuff
Version: 0.0.3
Summary: PYGame Stuff for writing pygame applications
Home-page: https://github.com/sustainablelab/pygstuff
Author: Mike Gazes
Author-email: sustainablelab@gmail.com
License: MIT
Platform: Windows
Platform: Mac
Platform: Linux
Classifier: Programming Language :: Python :: 3
Classifier: License :: OSI Approved :: MIT License
Classifier: Operating System :: OS Independent
Classifier: Development Status :: 1 - Planning
Classifier: Intended Audience :: Developers
Classifier: Topic :: Scientific/Engineering
Classifier: Topic :: Software Development :: User Interfaces
Classifier: Topic :: Software Development :: Libraries :: pygame
Requires-Python: >=3.7
Requires-Dist: pygame
